PyEIS/PyEIS.py
PyEIS/PyEIS_Advanced_tools.py
PyEIS/PyEIS_Data_extraction.py
PyEIS/PyEIS_Lin_KK.py
PyEIS/__init__.py
PyEIS-1.0.10.dist-info/LICENSE
PyEIS-1.0.10.dist-info/METADATA
PyEIS-1.0.10.dist-info/WHEEL
PyEIS-1.0.10.dist-info/top_level.txt
PyEIS-1.0.10.dist-info/RECORD
