Metadata-Version: 2.1
Name: PyEIS
Version: 1.0.10
Summary: A Python-based Electrochemical Impedance Spectroscopy simulator and analyzer
Home-page: https://github.com/kbknudsen/PyEIS
Author: Kristian B. Knudsen
Author-email: kknu@berkeley.edu
License: LICENSE
Platform: UNKNOWN
Classifier: Programming Language :: Python :: 3
Classifier: License :: OSI Approved :: Apache Software License
Classifier: Operating System :: OS Independent
